kouyou/__init__.py
kouyou/google/__init__.py
kouyou/google/drive.py
kouyou/google/sheets.py
kouyou/google/utils.py
kouyou-1.0.dist-info/LICENSE
kouyou-1.0.dist-info/WHEEL
kouyou-1.0.dist-info/METADATA
kouyou-1.0.dist-info/RECORD
