Metadata-Version: 2.1
Name: kouyou
Version: 1.0
Summary: My personal utils project (Kouyou - 効用 - Utility)
License: MIT
Author: Gustavo Reis
Author-email: guto.reisdelima@gmail.com
Requires-Python: >=3.8,<4.0
Classifier: License :: OSI Approved :: MIT License
Classifier: Programming Language :: Python :: 3
Classifier: Programming Language :: Python :: 3.8
Requires-Dist: google-api-python-client (>=1.7.11,<2.0.0)
Requires-Dist: gspread (>=3.2.0,<4.0.0)
Requires-Dist: numpy (>=1.18.1,<2.0.0)
Requires-Dist: oauth2client (>=4.1.3,<5.0.0)
Requires-Dist: openpyxl (>=3.0.3,<4.0.0)
Requires-Dist: pandas (>=1.0.1,<2.0.0)
Requires-Dist: python-dotenv (>=0.11.0,<0.12.0)
Requires-Dist: unidecode (>=1.1.1,<2.0.0)
